pyspotstream/__init__.py
pyspotstream/_version.py
pyspotstream/datasets/__init__.py
pyspotstream/datasets/_base.py
pyspotstream/datasets/_opm.py
pyspotstream/eval/__init__.py
pyspotstream/eval/_rm.py
pyspotstream/eval/evaluation.py
pyspotstream/misc/__init__.py
pyspotstream/misc/conventions.py
pyspotstream/misc/drift_generator.py
pyspotstream/plot/__init__.py
pyspotstream/plot/plotmulti.py
pyspotstream/plot/plotperformance.py
pyspotstream-0.2.0.dist-info/METADATA
pyspotstream-0.2.0.dist-info/WHEEL
pyspotstream-0.2.0.dist-info/top_level.txt
pyspotstream-0.2.0.dist-info/RECORD
