Metadata-Version: 2.1
Name: pyspotstream
Version: 0.2.0
Summary: A package for the experimental analysis of BML and OML algorithms.
Author-email: Aleksandr Subbotin <aleksandr.subbotin@th-koeln.de>, Noah Puetz <noah.c.puetz@gmail.com>, Olaf Mersmann <olafm@p-value.net>, "T. Bartz-Beielstein" <tbb@bartzundbartz.de>
License: AGPL-3.0-or-later
Project-URL: Homepage, https://www.spotseven.de
Project-URL: Issues, https://github.com/bartzbeielstein/pyspotstream/issues
Project-URL: Repository, https://github.com/bartzbeielstein/pyspotstream
Classifier: Programming Language :: Python :: 3.10
Classifier: Programming Language :: Python :: 3.11
Classifier: License :: OSI Approved :: GNU Affero General Public License v3 or later (AGPLv3+)
Classifier: Operating System :: OS Independent
Requires-Python: >=3.10
Requires-Dist: matplotlib (>=3.6.0)
Requires-Dist: numpy (>=1.23.0)
Requires-Dist: pandas (>=1.5.0)
Requires-Dist: river (>=0.14.0)
Requires-Dist: scikit-learn (>=1.2.0)
